AUTHORS
COPYING
ChangeLog
INSTALL
MANIFEST.in
README
TODO
app.c
app.h
base64.c
base64.h
buffer.c
buffer.h
epydoc.prj
errors.c
errors.h
keyinfo.c
keyinfo.h
keys.c
keys.h
keysdata.c
keysdata.h
keysmngr.c
keysmngr.h
list.c
list.h
membuf.c
membuf.h
nodeset.c
nodeset.h
openssl.h
parser.c
parser.h
setup.py
templates.c
templates.h
transforms.c
transforms.h
utils.c
utils.h
version.c
version.h
wrap_objs.c
wrap_objs.h
x509.c
x509.h
xmldsig.c
xmldsig.h
xmlenc.c
xmlenc.h
xmlsec.c
xmlsec.h
xmlsec.py
xmlsec_strings.py
xmlsecmod.c
xmlsecmod.h
xmltree.c
xmltree.h
examples/decrypt1.py
examples/decrypt2-res1.xml
examples/decrypt2-res2.xml
examples/decrypt2.py
examples/decrypt3.py
examples/deskey.bin
examples/encrypt1-res.xml
examples/encrypt1-tmpl.xml
examples/encrypt1.py
examples/encrypt2-doc.xml
examples/encrypt2-res.xml
examples/encrypt2.py
examples/encrypt3-doc.xml
examples/encrypt3-res.xml
examples/encrypt3.py
examples/pyxmlsec-demo.py
examples/rootcert.pem
examples/rsacert.pem
examples/rsakey.pem
examples/rsapub.pem
examples/sign1-res.xml
examples/sign1-tmpl.xml
examples/sign1.py
examples/sign2-doc.xml
examples/sign2-res.xml
examples/sign2.py
examples/sign3-doc.xml
examples/sign3-res.xml
examples/sign3.py
examples/verify1.py
examples/verify2.py
examples/verify3.py
examples/verify4-bad-res.xml
examples/verify4-bad-tmpl.xml
examples/verify4-res.xml
examples/verify4-tmpl.xml
examples/verify4.py
pyxmlsec_next.egg-info/PKG-INFO
pyxmlsec_next.egg-info/SOURCES.txt
pyxmlsec_next.egg-info/dependency_links.txt
pyxmlsec_next.egg-info/top_level.txt