Metadata-Version: 1.1
Name: pyxmlsec-next
Version: 0.3.1
Summary: Python bindings for XMLSec Library
Home-page: https://github.com/dnet/pyxmlsec
Author: Valery Febvre and others
Author-email: vfebvre@easter-eggs.com
License: GNU GPL
Platform: any
Classifier: Development Status :: 5 - Production/Stable
Classifier: Intended Audience :: Developers
Classifier: License :: OSI Approved :: GNU General Public License (GPL)
Classifier: Natural Language :: English
Classifier: Operating System :: POSIX
Classifier: Programming Language :: C
Classifier: Programming Language :: Python
Classifier: Topic :: Security
Classifier: Topic :: Software Development :: Libraries :: Python Modules
